vws_test_fixtures/__init__.py
vws_test_fixtures/different_high_quality_image.jpg
vws_test_fixtures/high_quality_image.jpg
vws_test_fixtures/images.py
vws_test_fixtures/plugin.py
vws_test_fixtures/py.typed
vws_test_fixtures-2023.3.5.dist-info/LICENSE
vws_test_fixtures-2023.3.5.dist-info/METADATA
vws_test_fixtures-2023.3.5.dist-info/WHEEL
vws_test_fixtures-2023.3.5.dist-info/entry_points.txt
vws_test_fixtures-2023.3.5.dist-info/top_level.txt
vws_test_fixtures-2023.3.5.dist-info/RECORD
