Metadata-Version: 2.1
Name: vws-test-fixtures
Version: 2023.3.5
Summary: Test fixtures for testing code which works with the Vuforia Web Services (VWS) API
Author-email: Adam Dangoor <adamdangoor@gmail.com>
License: MIT License
Project-URL: Source, https://github.com/VWS-Python/vws-test-fixtures
Keywords: vuforia,vws
Classifier: Operating System :: POSIX
Classifier: Environment :: Web Environment
Classifier: Programming Language :: Python :: 3.11
Classifier: License :: OSI Approved :: MIT License
Classifier: Development Status :: 5 - Production/Stable
Classifier: Framework :: Pytest
Requires-Python: >=3.10
License-File: LICENSE
Requires-Dist: Pillow
Requires-Dist: pytest
Provides-Extra: dev
Requires-Dist: Sphinx-Substitution-Extensions (==2022.2.16) ; extra == 'dev'
Requires-Dist: black (==23.1.0) ; extra == 'dev'
Requires-Dist: check-manifest (==0.49) ; extra == 'dev'
Requires-Dist: doc8 (==1.1.1) ; extra == 'dev'
Requires-Dist: freezegun (==1.2.2) ; extra == 'dev'
Requires-Dist: furo (==2022.12.7) ; extra == 'dev'
Requires-Dist: mypy (==1.0.1) ; extra == 'dev'
Requires-Dist: pip-check-reqs (==2.4.4) ; extra == 'dev'
Requires-Dist: pylint (==2.16.3) ; extra == 'dev'
Requires-Dist: pyroma (==4.2) ; extra == 'dev'
Requires-Dist: pytest-cov (==4.0.0) ; extra == 'dev'
Requires-Dist: ruff (==0.0.253) ; extra == 'dev'
Requires-Dist: sphinx-autodoc-typehints (==1.22) ; extra == 'dev'
Requires-Dist: sphinx (==6.1.3) ; extra == 'dev'
Requires-Dist: sphinx-prompt (==1.5.0) ; extra == 'dev'
Requires-Dist: sphinxcontrib.spelling (==8.0.0) ; extra == 'dev'
Requires-Dist: types-setuptools (==67.4.0.3) ; extra == 'dev'
Requires-Dist: types-Pillow (==9.4.0.17) ; extra == 'dev'
Requires-Dist: vulture (==2.7) ; extra == 'dev'
Provides-Extra: packaging
